PythonEasyProject/__init__.py
PythonEasyProject/app.py
PythonEasyProject/tests/__init__.py
PythonEasyProject/tests/integration_test.py
PythonEasyProject/tests/unit_test.py
PythonEasyApplication-0.0.4.dist-info/METADATA
PythonEasyApplication-0.0.4.dist-info/WHEEL
PythonEasyApplication-0.0.4.dist-info/top_level.txt
PythonEasyApplication-0.0.4.dist-info/RECORD
