Metadata-Version: 2.1
Name: PythonEasyApplication
Version: 0.0.4
Summary: Easy Application in Python
Home-page: https://gitlab.com/lemon9693650/pythoneasyproject.git
Author: ComiBesanaLevati
Requires-Dist: astroid ==2.15.8
Requires-Dist: attrs ==23.1.0
Requires-Dist: blinker ==1.6.3
Requires-Dist: certifi ==2023.7.22
Requires-Dist: cffi ==1.16.0
Requires-Dist: click ==8.1.7
Requires-Dist: colorama ==0.4.6
Requires-Dist: dill ==0.3.7
Requires-Dist: dodgy ==0.2.1
Requires-Dist: flake8 ==5.0.4
Requires-Dist: flake8-polyfill ==1.0.2
Requires-Dist: flask ==3.0.0
Requires-Dist: gitdb ==4.0.10
Requires-Dist: GitPython ==3.1.40
Requires-Dist: h11 ==0.14.0
Requires-Dist: idna ==3.4
Requires-Dist: iniconfig ==2.0.0
Requires-Dist: isort ==5.12.0
Requires-Dist: itsdangerous ==2.1.2
Requires-Dist: Jinja2 ==3.1.2
Requires-Dist: lazy-object-proxy ==1.9.0
Requires-Dist: MarkupSafe ==2.1.3
Requires-Dist: mccabe ==0.7.0
Requires-Dist: outcome ==1.2.0
Requires-Dist: packaging ==23.2
Requires-Dist: pep8-naming ==0.10.0
Requires-Dist: platformdirs ==3.11.0
Requires-Dist: pluggy ==1.3.0
Requires-Dist: prospector ==1.10.3
Requires-Dist: bandit ==1.7.5
Requires-Dist: wheel ==0.41.2
Requires-Dist: setuptools ==68.2.2
Requires-Dist: pycodestyle ==2.9.1
Requires-Dist: pycparser ==2.21
Requires-Dist: pydocstyle ==6.3.0
Requires-Dist: pyflakes ==2.5.0
Requires-Dist: pylint ==2.17.7
Requires-Dist: pylint-celery ==0.3
Requires-Dist: pylint-django ==2.5.3
Requires-Dist: pylint-flask ==0.6
Requires-Dist: pylint-plugin-utils ==0.7
Requires-Dist: PySocks ==1.7.1
Requires-Dist: pytest ==7.4.2
Requires-Dist: PyYAML ==6.0.1
Requires-Dist: requirements-detector ==1.2.2
Requires-Dist: selenium ==4.14.0
Requires-Dist: semver ==3.0.2
Requires-Dist: setoptconf-tmp ==0.3.1
Requires-Dist: smmap ==5.0.1
Requires-Dist: sniffio ==1.3.0
Requires-Dist: snowballstemmer ==2.2.0
Requires-Dist: sortedcontainers ==2.4.0
Requires-Dist: toml ==0.10.2
Requires-Dist: tomlkit ==0.12.1
Requires-Dist: trio ==0.22.2
Requires-Dist: trio-websocket ==0.11.1
Requires-Dist: pdoc ==14.1.0
Requires-Dist: twine ==5.1.1
Requires-Dist: urllib3 ==2.0.6
Requires-Dist: Werkzeug ==3.0.0
Requires-Dist: wrapt ==1.15.0
Requires-Dist: wsproto ==1.2.0
